schemaforge/__init__.py
schemaforge/client.py
schemaforge/version.py
schemaforge/exceptions/__init__.py
schemaforge/exceptions/api_error.py
schemaforge/models/__init__.py
schemaforge/models/request.py
schemaforge/models/response.py
schemaforge/utils/__init__.py
schemaforge/utils/api_utils.py
schemaforge/utils/config.py
schemaforge/utils/model_loader.py
schemaforge-0.1.1.dist-info/METADATA
schemaforge-0.1.1.dist-info/WHEEL
schemaforge-0.1.1.dist-info/top_level.txt
schemaforge-0.1.1.dist-info/RECORD
