Metadata-Version: 2.4
Name: schemaforge
Version: 0.1.1
Summary: SchemaForge Python SDK
Home-page: https://github.com/X-Zero-L/schemaforge-sdk
Author: SchemaForge Team
Author-email: info@schemaforge.ai
Requires-Python: >=3.9
Requires-Dist: aiohttp>=3.11.14
Requires-Dist: pydantic[all,email]>=2.10.6
Requires-Dist: requests>=2.32.3
Requires-Dist: setuptools>=78.0.2
Dynamic: author
Dynamic: author-email
Dynamic: home-page
Dynamic: requires-python
